packagediscovery/__init__.py
packagediscovery/packages.py
packagediscovery/py.typed
packagediscovery/setuptools.py
packagediscovery-0.2.0.dist-info/licenses/LICENSE
packagediscovery-0.2.0.dist-info/METADATA
packagediscovery-0.2.0.dist-info/WHEEL
packagediscovery-0.2.0.dist-info/top_level.txt
packagediscovery-0.2.0.dist-info/RECORD
