Metadata-Version: 2.4
Name: packagediscovery
Version: 0.2.0
Summary: Package discovery based on Setuptools.
Author-email: Yukihiko Shinoda <yuk.hik.future@gmail.com>
Maintainer-email: Yukihiko Shinoda <yuk.hik.future@gmail.com>
License: MIT License
Project-URL: homepage, https://github.com/yukihiko-shinoda/package-discovery
Project-URL: repository, https://github.com/yukihiko-shinoda/package-discovery
Keywords: setuptools,package,discovery
Classifier: Development Status :: 4 - Beta
Classifier: Intended Audience :: Developers
Classifier: License :: OSI Approved :: MIT License
Classifier: Natural Language :: English
Classifier: Operating System :: OS Independent
Classifier: Programming Language :: Python
Classifier: Programming Language :: Python :: 3
Classifier: Programming Language :: Python :: 3.7
Classifier: Programming Language :: Python :: 3.8
Classifier: Programming Language :: Python :: 3.9
Classifier: Programming Language :: Python :: 3.10
Classifier: Programming Language :: Python :: 3.11
Classifier: Programming Language :: Python :: 3.12
Classifier: Programming Language :: Python :: 3.13
Classifier: Topic :: Software Development
Classifier: Topic :: Software Development :: Build Tools
Classifier: Topic :: Software Development :: Debuggers
Classifier: Topic :: Software Development :: Testing
Classifier: Topic :: Software Development :: Libraries
Classifier: Topic :: Software Development :: Libraries :: Python Modules
Classifier: Topic :: System :: Software Distribution
Classifier: Topic :: Utilities
Classifier: Typing :: Typed
Requires-Python: >=3.7
License-File: LICENSE
Requires-Dist: setuptools>=61.0.0
Dynamic: license-file
